{
    "lawyer_name":"السيرة الذاتية للمحامي محمد مكي",
    "learn":{
        "learn_1":{
            "type":"اجازة في الحقوق",
            "year":"1999",
            "university":"جامعة بيروت العربيه"
        },
        "learn_2":{
            "type":"الانتساب للنقابة",
            "year":"2021",
            "university":"منتسب إلى نقابة المحامين في بيروت منذ عام 2021"
        }

    },
    "experience":{
        "experience_1":"رئيس الجمعية الوطنيه الاسلاميه.",
        "experience_2":"رئيس جمعية ال مكي وانسباؤهم.",
        "experience_3":"امين سر ملتقى الجمعيات البيروتيه.",
        "experience_4":"رئيس لجنة المساءلة والتأديب في الاتحاد الآسيوي للجمباز.",
        "experience_5":"رئيس اللجنة القانونيه في الاتحاد العربي للجمباز.",
        "experience_6":"نائب رئيس الاتحاد اللبناني للجمباز."
    }
}